calculation/__init__.py
calculation/area.py
calculation/distance.py
calculation/exif_calc_heading.py
calculation/geospatial_utils.py
calculation/intersection.py
calculation/iterator.py
calculation/units.py
calculation/util.py
calculation/utilities.py
calculation/version.py
calculation_mapilio-0.1.42.dist-info/METADATA
calculation_mapilio-0.1.42.dist-info/WHEEL
calculation_mapilio-0.1.42.dist-info/top_level.txt
calculation_mapilio-0.1.42.dist-info/RECORD
