Metadata-Version: 2.1
Name: calculation-mapilio
Version: 0.1.42
Summary: Mapilio Calculation Library
Home-page: https://github.com/mapilio/calculation.git
Author: Mapilio - Ozcan Durak & MCV
Author-email: ozcan@visiosoft.com.tr
License: MIT
Project-URL: Bug Reports, https://github.com/mapilio/calculation/issues
Project-URL: Say Thanks!, https://mapilio.com/#contact
Project-URL: Source, https://github.com/mapilio/calculation/
Requires-Python: >=3.6, <4
Requires-Dist: numpy
Requires-Dist: requests
Requires-Dist: trianglesolver
Requires-Dist: ExifRead
Requires-Dist: addict
